stitchclient/__init__.py
stitchclient/client.py
python_stitch_client-0.8.0.post1.dist-info/LICENSE
python_stitch_client-0.8.0.post1.dist-info/WHEEL
python_stitch_client-0.8.0.post1.dist-info/METADATA
python_stitch_client-0.8.0.post1.dist-info/RECORD
