Metadata-Version: 2.1
Name: python-stitch-client
Version: 0.8.0.post1
Summary: Library for working with the stitch client in python
Home-page: https://github.com/NarrativeScience/python-stitch-client
License: UNKNOWN
Author: Narrative Science
Author-email: devops@narrativescience.com
Requires-Python: >=3.5.7,<4
Classifier: Programming Language :: Python :: 3 :: Only
Requires-Dist: python-dateutil==2.6.1
Requires-Dist: msgpack-python
Requires-Dist: requests==2.24.0
